Metadata-Version: 1.1
Name: ofxstatement-postfinance
Version: 0.0.1
Summary: ofxstatement for Post Finance (Swiss)
Home-page: https://github.com/maxandersen/ofxstatement-postfinance
Author: Max Rydahl Andersen
Author-email: python@xam.dk
License: GPLv3
Keywords: ofx,banking,statement,swiss,post
Platform: UNKNOWN
Classifier: Development Status :: 3 - Alpha
Classifier: Programming Language :: Python :: 3
Classifier: Natural Language :: English
Classifier: Topic :: Office/Business :: Financial :: Accounting
Classifier: Topic :: Utilities
Classifier: Environment :: Console
Classifier: Operating System :: OS Independent
Classifier: License :: OSI Approved :: GNU Affero General Public License v3
